codetype/__init__.py
codetype/re_globals.py
codetype/signatures/AppleScript.bin
codetype/signatures/C#.bin
codetype/signatures/C++.bin
codetype/signatures/C.bin
codetype/signatures/D.bin
codetype/signatures/Go.bin
codetype/signatures/Haskell.bin
codetype/signatures/Java.bin
codetype/signatures/JavaScript.bin
codetype/signatures/Julia.bin
codetype/signatures/Lua.bin
codetype/signatures/OCaml.bin
codetype/signatures/Objective-C.bin
codetype/signatures/PHP.bin
codetype/signatures/Perl.bin
codetype/signatures/Python.bin
codetype/signatures/R.bin
codetype/signatures/Ruby.bin
codetype/signatures/Rust.bin
codetype/signatures/Scala.bin
codetype/signatures/Swift.bin
codetype-1.0.1.data/scripts/codetype
codetype-1.0.1.dist-info/DESCRIPTION.rst
codetype-1.0.1.dist-info/METADATA
codetype-1.0.1.dist-info/RECORD
codetype-1.0.1.dist-info/WHEEL
codetype-1.0.1.dist-info/metadata.json
codetype-1.0.1.dist-info/top_level.txt
