Metadata-Version: 2.0
Name: codetype
Version: 1.0.1
Summary: A source code identification tool.
Home-page: https://github.com/jdkato/codetype
Author: Joseph Kato
Author-email: joseph@jdkato.io
License: MIT
Download-URL: https://github.com/jdkato/codetype/releases
Keywords: classifying,identification,code
Platform: UNKNOWN
Classifier: License :: OSI Approved :: MIT License
Classifier: Programming Language :: Python :: 2.7
Classifier: Programming Language :: Python :: 3.4
Classifier: Programming Language :: Python :: 3.5
Requires-Dist: msgpack-python
